anaconda_cloud/__init__.py
anaconda_cloud/_version.py
anaconda_cloud-0.2.0.dist-info/METADATA
anaconda_cloud-0.2.0.dist-info/WHEEL
anaconda_cloud-0.2.0.dist-info/licenses/LICENSE
anaconda_cloud-0.2.0.dist-info/RECORD
