Metadata-Version: 2.3
Name: anaconda-cloud
Version: 0.2.0
Summary: Anaconda Cloud client tools
License: BSD-3-Clause
License-File: LICENSE
Requires-Python: >=3.8
Requires-Dist: anaconda-cli-base
Requires-Dist: anaconda-cloud-auth
